slack_export_viewer-3.5.0.dist-info/licenses/LICENSE
slackviewer/__init__.py
slackviewer/app.py
slackviewer/archive.py
slackviewer/cli.py
slackviewer/config.py
slackviewer/constants.py
slackviewer/formatter.py
slackviewer/freezer.py
slackviewer/main.py
slackviewer/message.py
slackviewer/reader.py
slackviewer/user.py
slackviewer/static/viewer.css
slackviewer/templates/example_template_single_export.html
slackviewer/templates/export_single.html
slackviewer/templates/util.html
slackviewer/templates/viewer.html
slackviewer/utils/__init__.py
slackviewer/utils/six.py
slack_export_viewer-3.5.0.dist-info/METADATA
slack_export_viewer-3.5.0.dist-info/WHEEL
slack_export_viewer-3.5.0.dist-info/entry_points.txt
slack_export_viewer-3.5.0.dist-info/top_level.txt
slack_export_viewer-3.5.0.dist-info/RECORD
